mzy_py/__init__.py
mzy_py/core.py
mzy_py/server.py
mzy_py/utils.py
mzy_py-0.2.6.dist-info/LICENSE
mzy_py-0.2.6.dist-info/METADATA
mzy_py-0.2.6.dist-info/WHEEL
mzy_py-0.2.6.dist-info/top_level.txt
mzy_py-0.2.6.dist-info/RECORD
